[
  {
    "title": "Wykroczenie",
    "price": null,
    "priceToDetermined": true,
    "categoryId": 161,
    "category": {
      "name": "Sprawy sądowe",
      "description": null,
      "parentId": 2,
      "parent": {
        "name": "Sprawy prywatne",
        "description": null,
        "parentId": null,
        "parent": null,
        "level": 1,
        "id": 2
      },
      "level": 2,
      "id": 161
    },
    "description": "Sąd Rejonowy w Przasnyszu\r\nPILNE!\r\n14.07.2023r. Godz. 10:00\r\nwykroczenie; możliwe, że sprawa zostanie jutro zakończona",
    "addressId": 25,
    "address": {
      "postalCode": "18-400",
      "street": "Dworna 16",
      "city": "Łomża",
      "province": "Podlaskie",
      "simcId": 99210,
      "simc": null,
      "jobId": null,
      "job": null,
      "id": 25
    },
    "jobType": 1,
    "courtId": 7,
    "court": {
      "type": 1,
      "name": "Sąd Okręgowy w Łomży",
      "street": "Dworna 16",
      "postalCode": "18-400",
      "city": "Łomża",
      "province": "podlaskie",
      "phone": "(86) 216 62 81 do 84",
      "fax": "(86) 216 67 53",
      "email": "boi@lomza.so.gov.pl",
      "simcId": 99210,
      "simc": null,
      "id": 7
    },
    "courtDepartment": null,
    "date": "2023-07-14T00:00:00",
    "time": "12:45:00",
    "dateToDetermined": false,
    "email": "bartes19@gmail.com",
    "phone": "666293279",
    "proffesionTypes": [
      3,
      2,
      4,
      1
    ],
    "vatInvoice": true,
    "insurance": false,
    "nameOrCompany": null,
    "offers": [],
    "status": 0,
    "createdDate": "2023-07-13T08:43:07.6860145",
    "createdById": "ca6b5be9-df19-4a37-bd85-3028e68f73c2",
    "createdBy": null,
    "isActive": true,
    "id": 11
  }
]